<?xml version="1.0" encoding="UTF-8"?>
<cc_theme xmlns:xi="http://alvin.goanimate.org/store" xmlns:xsi="http://www.w3.org/2001/XMLSchema-instance" id="infographics" studio_theme_id="infographics" name="Business as Visual" version="2.0" xsi:noNamespaceSchemaLocation="http://alvin.goanimate.org/schema/cc_library_theme.xsd">
<!-- https://docs.google.com/a/goanimate.com/spreadsheet/ccc?key=0Aina-o_ZDKZAdFA0T0hVa2tDOFJGSjJKa1UyRGxnS2c&usp=drive_web#gid=6  -->

    <color r="ccSkinColor" component_type="bodyshape" enable="Y">
        <choice>0xFFF9EC</choice>
		<choice>0xFEEDD3</choice>
        <choice>0xEAD2B0</choice>
        <choice>0xEBC9AF</choice>
        <choice>0xE2C294</choice>
        <choice>0xCE9D7D</choice>
        <choice>0xAC8151</choice>
        <choice>0x8d6850</choice>
    </color>
    <color r="ccFaceHairColor" component_type="bodyshape" enable="Y">
        <choice>0xF2E784</choice>
        <choice>0xE3EEF4</choice>
        <choice>0x7E4D1B</choice>
        <choice>0x321F1B</choice>
        <choice>0x9AB03E</choice>
        <choice>0xC48888</choice>
        <choice>0xBA4545</choice>
        <choice>0x6C5E91</choice>
    </color>
    <color r="ccEyeLib" component_type="eye" parent_color_r="ccSkinColor" parent_component_type="bodyshape" enable="N">
        <choice>0x5F3F29</choice>
        <choice>0xBD8764</choice>
        <choice>0x80DCE6</choice>
        <choice>0x99CC00</choice>
        <choice>0x1E447B</choice>
        <choice>0x996666</choice>
        <choice>0xE47070</choice>
        <choice>0x4B0156</choice>
    </color>
    <color r="ccEyeIris" component_type="eye" enable="N">
        <choice>0x988986</choice>
        <choice>0x229188</choice>
        <choice>0x7D551C</choice>
        <choice>0x9966CC</choice>
        <choice>0x7892C6</choice>
        <choice>0x993333</choice>
        <choice>0x669900</choice>
        <choice>0xEA7B9D</choice>
    </color>
    <color r="ccGlassesFrame" component_type="glasses" enable="N">
        <choice>0xAE0057</choice>
        <choice>0x53A8DF</choice>
        <choice>0xEC9EC5</choice>
        <choice>0x360202</choice>
        <choice>0xC1BFB8</choice>
        <choice>0x5F4929</choice>
        <choice>0x4A6028</choice>
        <choice>0x000000</choice>
    </color>
    <color r="ccGlassesLens" component_type="glasses" enable="N">
        <choice>0xFFFFFF</choice>
        <choice>0x555555</choice>
        <choice>0xBC6A70</choice>
        <choice>0x360202</choice>
        <choice>0xC1BFB8</choice>
        <choice>0xFFCC00</choice>
        <choice>0x640F0F</choice>
        <choice>0x000000</choice>
    </color>
    <color r="ccMouthLip" component_type="mouth" enable="N">
        <choice>0xB7796A</choice>
        <choice>0x9A6C46</choice>
        <choice>0xCA3030</choice>
        <choice>0x73263E</choice>
        <choice>0xE47070</choice>
        <choice>0x891212</choice>
        <choice>0x7D5134</choice>
        <choice>0xEB8369</choice>
    </color>
    <color r="ccEyebrow" component_type="eyebrow" enable="N">
        <choice>0x7E4D1B</choice>
        <choice>0x483315</choice>
        <choice>0x421D0B</choice>
        <choice>0x321F1B</choice>
        <choice>0x151515</choice>
        <choice>0xBA4545</choice>
        <choice>0x494576</choice>
        <choice>0x6D3434</choice>
    </color>
    <color r="ccHairMajor" component_type="hair" enable="Y">
        <choice>0xFBFFFE</choice>
        <choice>0x763634</choice>
        <choice>0x2E2A41</choice>
        <choice>0xCD9A31</choice>
        <choice>0x615C3F</choice>
        <choice>0x341E18</choice>
        <choice>0x7E4937</choice>
        <choice>0x3C3C3C</choice>
    </color>
    <color r="ccHairMinor" component_type="hair" enable="Y">
        <choice>0xFEFEFE</choice>
        <choice>0x2F9AC4</choice>
        <choice>0x3DD17D</choice>
        <choice>0xDE5C5C</choice>
        <choice>0xD0A12D</choice>
        <choice>0x366B40</choice>
        <choice>0x8A2828</choice>
        <choice>0x3C3C3C</choice>
    </color>
    <color r="ccUpperMain" component_type="GoUpper" enable="Y">
        <choice>0x67737F</choice>
        <choice>0xF3D64E</choice>
        <choice>0x1BA67C</choice>
        <choice>0xDA4A42</choice>
        <choice>0x1B336F</choice>
        <choice>0xFFF8E0</choice>
        <choice>0x3F3F33</choice>
        <choice>0x5B1934</choice>
    </color>
    <color r="ccUpperMinor" component_type="GoUpper" enable="Y">
        <choice>0xFEFEFE</choice>
        <choice>0x3A552A</choice>
        <choice>0xFF4052</choice>
        <choice>0x08594A</choice>
        <choice>0xC6C946</choice>
        <choice>0x48BAD2</choice>
        <choice>0xA27B50</choice>
        <choice>0x3C3C3C</choice>
    </color>
    <color r="ccLowerMainA" component_type="GoLower" enable="Y">
        <choice>0xFFFDFE</choice>
        <choice>0xA4A4A4</choice>
        <choice>0xCD9600</choice>
        <choice>0x6A4D3B</choice>
        <choice>0x50505A</choice>
        <choice>0x5D6031</choice>
        <choice>0x420B21</choice>
        <choice>0x3F3B38</choice>
    </color>
    <color r="ccLowerMain" component_type="GoLower" enable="N">
        <choice>0xFFFEFF</choice>
        <choice>0x4F5157</choice>
        <choice>0xA4A4A4</choice>
        <choice>0x5E5F34</choice>
        <choice>0xFF87A3</choice>
        <choice>0xCC9966</choice>
        <choice>0x65503B</choice>
        <choice>0x3C3C3C</choice>
    </color>
    <color r="ccLowerMinor" component_type="GoLower" enable="N">
        <choice>0xFFF3FF</choice>
        <choice>0x4F5157</choice>
        <choice>0xA4A4A4</choice>
        <choice>0x99DAD8</choice>
        <choice>0xFCD0DA</choice>
        <choice>0x9474A8</choice>
        <choice>0x65503B</choice>
        <choice>0x3C3C3C</choice>
    </color>
<!--
    <color r="ccDecMajor" component_type="facedecoration" enable="N">
        <choice>0xAE0057</choice>
        <choice>0x53A8DF</choice>
        <choice>0xEC9EC5</choice>
        <choice>0x360202</choice>
        <choice>0xC1BFB8</choice>
        <choice>0x5F4929</choice>
        <choice>0x4A6028</choice>
        <choice>0x000000</choice>
    </color>
    <color r="ccDecMinor" component_type="facedecoration" enable="N">
        <choice>0xFFFFFF</choice>
        <choice>0x555555</choice>
        <choice>0xBC6A70</choice>
        <choice>0x360202</choice>
        <choice>0xC1BFB8</choice>
        <choice>0xFFCC00</choice>
        <choice>0x640F0F</choice>
        <choice>0x000000</choice>
    </color>
    <color r="ccBackMajor" component_type="GoBehindBody" enable="Y">
        <choice>0xAE0057</choice>
        <choice>0x53A8DF</choice>
        <choice>0xEC9EC5</choice>
        <choice>0x360202</choice>
        <choice>0xC1BFB8</choice>
        <choice>0x5F4929</choice>
        <choice>0x4A6028</choice>
        <choice>0x000000</choice>
    </color>
    <color r="ccBackMinor" component_type="GoBehindBody" enable="Y">
        <choice>0xFFFFFF</choice>
        <choice>0x555555</choice>
        <choice>0xBC6A70</choice>
        <choice>0x360202</choice>
        <choice>0xC1BFB8</choice>
        <choice>0xFFCC00</choice>
        <choice>0x640F0F</choice>
        <choice>0x000000</choice>
    </color>
-->
    <color r="ccHandMain" component_type="GoHands" enable="Y">
        <choice>0x2F2F2F</choice>
        <choice>0xB80303</choice>
        <choice>0x5B88B5</choice>
        <choice>0x94C422</choice>
        <choice>0xE8E9E2</choice>
        <choice>0x67564B</choice>
        <choice>0xBE5A30</choice>
        <choice>0xE797B6</choice>
    </color>
    <color r="ccFeetMain" component_type="GoFeet" enable="Y">
        <choice>0x151515</choice>
        <choice>0x323232</choice>
        <choice>0x462F2F</choice>
        <choice>0x543C2E</choice>
        <choice>0x4A2F58</choice>
        <choice>0x481818</choice>
        <choice>0x3E5121</choice>
        <choice>0x8A451B</choice>
    </color>

	<facial id="head_angry_front" name="Face Camera - Angry" enable="N">
        <selection type="ear" state_id="front_default"/>
        <selection type="eye" state_id="front_default"/>
        <selection type="eyebrow" state_id="front_angry"/>
        <selection type="faceshape" state_id="front_default"/>
        <selection type="glasses" state_id="front_default"/>
        <selection type="hair" state_id="front_default"/>
        <selection type="mouth" state_id="front_angry"/>
        <selection type="nose" state_id="front_default"/>
        <selection type="facedecoration" state_id="front_default"/>
    </facial>
	<facial id="head_confused_front" name="Face Camera - Confused" enable="N">
        <selection type="ear" state_id="front_default"/>
        <selection type="eye" state_id="front_default"/>
        <selection type="eyebrow" state_id="front_confused"/>
        <selection type="faceshape" state_id="front_default"/>
        <selection type="glasses" state_id="front_default"/>
        <selection type="hair" state_id="front_default"/>
        <selection type="mouth" state_id="front_angry"/>
        <selection type="nose" state_id="front_default"/>
        <selection type="facedecoration" state_id="front_default"/>
    </facial>
	<facial id="head_cry_front" name="Face Camera - Desperate" enable="N">
        <selection type="ear" state_id="front_default"/>
        <selection type="eye" state_id="front_cry"/>
        <selection type="eyebrow" state_id="front_sad"/>
        <selection type="faceshape" state_id="front_default"/>
        <selection type="glasses" state_id="front_default"/>
        <selection type="hair" state_id="front_default"/>
        <selection type="mouth" state_id="front_cry"/>
        <selection type="nose" state_id="front_default"/>
        <selection type="facedecoration" state_id="front_default"/>
    </facial>
	<facial id="head_happy_front" name="Face Camera - Happy" enable="N">
        <selection type="ear" state_id="front_default"/>
        <selection type="eye" state_id="front_default"/>
        <selection type="eyebrow" state_id="front_default"/>
        <selection type="faceshape" state_id="front_default"/>
        <selection type="glasses" state_id="front_default"/>
        <selection type="hair" state_id="front_default"/>
        <selection type="mouth" state_id="front_happy"/>
        <selection type="nose" state_id="front_default"/>
        <selection type="facedecoration" state_id="front_default"/>
    </facial>
	<facial id="head_neutral_front" name="Face Camera - Neutral" enable="N">
        <selection type="ear" state_id="front_default"/>
        <selection type="eye" state_id="front_default"/>
        <selection type="eyebrow" state_id="front_default"/>
        <selection type="faceshape" state_id="front_default"/>
        <selection type="glasses" state_id="front_default"/>
        <selection type="hair" state_id="front_default"/>
        <selection type="mouth" state_id="front_default"/>
        <selection type="nose" state_id="front_default"/>
        <selection type="facedecoration" state_id="front_default"/>
    </facial>
	<facial id="head_sad_front" name="Face Camera - Sad" enable="N">
        <selection type="ear" state_id="front_default"/>
        <selection type="eye" state_id="front_default"/>
        <selection type="eyebrow" state_id="front_sad"/>
        <selection type="faceshape" state_id="front_default"/>
        <selection type="glasses" state_id="front_default"/>
        <selection type="hair" state_id="front_default"/>
        <selection type="mouth" state_id="front_sad"/>
        <selection type="nose" state_id="front_default"/>
        <selection type="facedecoration" state_id="front_default"/>
    </facial>
	<facial id="head_sick_front" name="Face Camera - Sick" enable="N">
        <selection type="ear" state_id="front_default"/>
        <selection type="eye" state_id="front_sick"/>
        <selection type="eyebrow" state_id="front_sick"/>
        <selection type="faceshape" state_id="front_default"/>
        <selection type="glasses" state_id="front_default"/>
        <selection type="hair" state_id="front_default"/>
        <selection type="mouth" state_id="front_sick"/>
        <selection type="nose" state_id="front_default"/>
        <selection type="facedecoration" state_id="front_default"/>
    </facial>
	<facial id="head_talk_front" name="Face Camera - Talk" enable="N">
        <selection type="ear" state_id="front_default"/>
        <selection type="eye" state_id="front_talk"/>
        <selection type="eyebrow" state_id="front_talk"/>
        <selection type="faceshape" state_id="front_default"/>
        <selection type="glasses" state_id="front_default"/>
        <selection type="hair" state_id="front_default"/>
        <selection type="mouth" state_id="front_talk"/>
        <selection type="nose" state_id="front_default"/>
        <selection type="facedecoration" state_id="front_default"/>
    </facial>
	<facial id="head_talk_sad_front" name="Face Camera - Talk Sad" enable="N">
        <selection type="ear" state_id="front_default"/>
        <selection type="eye" state_id="front_default"/>
        <selection type="eyebrow" state_id="front_sad"/>
        <selection type="faceshape" state_id="front_default"/>
        <selection type="glasses" state_id="front_default"/>
        <selection type="hair" state_id="front_default"/>
        <selection type="mouth" state_id="front_talk"/>
        <selection type="nose" state_id="front_default"/>
        <selection type="facedecoration" state_id="front_default"/>
    </facial>
	<facial id="head_talk_angry_front" name="Face Camera - Talk Angry" enable="N">
        <selection type="ear" state_id="front_default"/>
        <selection type="eye" state_id="front_default"/>
        <selection type="eyebrow" state_id="front_angry"/>
        <selection type="faceshape" state_id="front_default"/>
        <selection type="glasses" state_id="front_default"/>
        <selection type="hair" state_id="front_default"/>
        <selection type="mouth" state_id="front_talk"/>
        <selection type="nose" state_id="front_default"/>
        <selection type="facedecoration" state_id="front_default"/>
	</facial>
	<facial id="head_sleep_front" name="Face Camera - Sleep" enable="N">
        <selection type="ear" state_id="front_default"/>
        <selection type="eye" state_id="front_sleep"/>
        <selection type="eyebrow" state_id="front_default"/>
        <selection type="faceshape" state_id="front_default"/>
        <selection type="glasses" state_id="front_default"/>
        <selection type="hair" state_id="front_default"/>
        <selection type="mouth" state_id="front_sleep"/>
        <selection type="nose" state_id="front_default"/>
        <selection type="facedecoration" state_id="front_default"/>
	</facial>
	<facial id="head_lookdown_front" name="Face Camera - Look Down" enable="N">
        <selection type="ear" state_id="front_default"/>
        <selection type="eye" state_id="front_look_down"/>
        <selection type="eyebrow" state_id="front_default"/>
        <selection type="faceshape" state_id="front_default"/>
        <selection type="glasses" state_id="front_default"/>
        <selection type="hair" state_id="front_default"/>
        <selection type="mouth" state_id="front_default"/>
        <selection type="nose" state_id="front_default"/>
        <selection type="facedecoration" state_id="front_default"/>
	</facial>
	<facial id="head_scheme_front" name="Face Camera - Scheming" enable="N">
        <selection type="ear" state_id="front_default"/>
        <selection type="eye" state_id="front_scheme"/>
        <selection type="eyebrow" state_id="front_scheme"/>
        <selection type="faceshape" state_id="front_default"/>
        <selection type="glasses" state_id="front_default"/>
        <selection type="hair" state_id="front_default"/>
        <selection type="mouth" state_id="front_scheme"/>
        <selection type="nose" state_id="front_default"/>
        <selection type="facedecoration" state_id="front_default"/>
	</facial>

	<facial id="head_angry_side" name="3/4 Front View - Angry" enable="N">
        <selection type="ear" state_id="side_default"/>
        <selection type="eye" state_id="side_default"/>
        <selection type="eyebrow" state_id="side_angry"/>
        <selection type="faceshape" state_id="side_default"/>
        <selection type="glasses" state_id="side_default"/>
        <selection type="hair" state_id="side_default"/>
        <selection type="mouth" state_id="side_angry"/>
        <selection type="nose" state_id="side_default"/>
        <selection type="facedecoration" state_id="side_default"/>
    </facial>
	<facial id="head_confused_side" name="3/4 Front View - Confused" enable="N">
        <selection type="ear" state_id="side_default"/>
        <selection type="eye" state_id="side_default"/>
        <selection type="eyebrow" state_id="side_confused"/>
        <selection type="faceshape" state_id="side_default"/>
        <selection type="glasses" state_id="side_default"/>
        <selection type="hair" state_id="side_default"/>
        <selection type="mouth" state_id="side_angry"/>
        <selection type="nose" state_id="side_default"/>
        <selection type="facedecoration" state_id="side_default"/>
    </facial>
	<facial id="head_cry_side" name="3/4 Front View - Desperate" enable="N">
        <selection type="ear" state_id="side_default"/>
        <selection type="eye" state_id="side_cry"/>
        <selection type="eyebrow" state_id="side_sad"/>
        <selection type="faceshape" state_id="side_default"/>
        <selection type="glasses" state_id="side_default"/>
        <selection type="hair" state_id="side_default"/>
        <selection type="mouth" state_id="side_cry"/>
        <selection type="nose" state_id="side_default"/>
        <selection type="facedecoration" state_id="side_default"/>
    </facial>
	<facial id="head_happy_side" name="3/4 Front View - Happy" enable="N">
        <selection type="ear" state_id="side_default"/>
        <selection type="eye" state_id="side_default"/>
        <selection type="eyebrow" state_id="side_default"/>
        <selection type="faceshape" state_id="side_default"/>
        <selection type="glasses" state_id="side_default"/>
        <selection type="hair" state_id="side_default"/>
        <selection type="mouth" state_id="side_happy"/>
        <selection type="nose" state_id="side_default"/>
        <selection type="facedecoration" state_id="side_default"/>
    </facial>
	<facial id="head_neutral_side" name="3/4 Front View - Neutral" enable="N">
        <selection type="ear" state_id="side_default"/>
        <selection type="eye" state_id="side_default"/>
        <selection type="eyebrow" state_id="side_default"/>
        <selection type="faceshape" state_id="side_default"/>
        <selection type="glasses" state_id="side_default"/>
        <selection type="hair" state_id="side_default"/>
        <selection type="mouth" state_id="side_default"/>
        <selection type="nose" state_id="side_default"/>
        <selection type="facedecoration" state_id="side_default"/>
    </facial>
	<facial id="head_sad_side" name="3/4 Front View - Sad" enable="N">
        <selection type="ear" state_id="side_default"/>
        <selection type="eye" state_id="side_default"/>
        <selection type="eyebrow" state_id="side_sad"/>
        <selection type="faceshape" state_id="side_default"/>
        <selection type="glasses" state_id="side_default"/>
        <selection type="hair" state_id="side_default"/>
        <selection type="mouth" state_id="side_sad"/>
        <selection type="nose" state_id="side_default"/>
        <selection type="facedecoration" state_id="side_default"/>
    </facial>
	<facial id="head_sick_side" name="3/4 Front View - Sick" enable="N">
        <selection type="ear" state_id="side_default"/>
        <selection type="eye" state_id="side_sick"/>
        <selection type="eyebrow" state_id="side_sick"/>
        <selection type="faceshape" state_id="side_default"/>
        <selection type="glasses" state_id="side_default"/>
        <selection type="hair" state_id="side_default"/>
        <selection type="mouth" state_id="side_sick"/>
        <selection type="nose" state_id="side_default"/>
        <selection type="facedecoration" state_id="side_default"/>
    </facial>
	<facial id="head_talk_side" name="3/4 Front View - Talk" enable="N">
        <selection type="ear" state_id="side_default"/>
        <selection type="eye" state_id="side_talk"/>
        <selection type="eyebrow" state_id="side_talk"/>
        <selection type="faceshape" state_id="side_default"/>
        <selection type="glasses" state_id="side_default"/>
        <selection type="hair" state_id="side_default"/>
        <selection type="mouth" state_id="side_talk"/>
        <selection type="nose" state_id="side_default"/>
        <selection type="facedecoration" state_id="side_default"/>
    </facial>
	<facial id="head_talk_sad_side" name="3/4 Front View - Talk Sad" enable="N">
        <selection type="ear" state_id="side_default"/>
        <selection type="eye" state_id="side_default"/>
        <selection type="eyebrow" state_id="side_sad"/>
        <selection type="faceshape" state_id="side_default"/>
        <selection type="glasses" state_id="side_default"/>
        <selection type="hair" state_id="side_default"/>
        <selection type="mouth" state_id="side_talk"/>
        <selection type="nose" state_id="side_default"/>
        <selection type="facedecoration" state_id="side_default"/>
    </facial>
	<facial id="head_talk_angry_side" name="3/4 Front View - Talk Angry" enable="N">
        <selection type="ear" state_id="side_default"/>
        <selection type="eye" state_id="side_default"/>
        <selection type="eyebrow" state_id="side_angry"/>
        <selection type="faceshape" state_id="side_default"/>
        <selection type="glasses" state_id="side_default"/>
        <selection type="hair" state_id="side_default"/>
        <selection type="mouth" state_id="side_talk"/>
        <selection type="nose" state_id="side_default"/>
        <selection type="facedecoration" state_id="side_default"/>
	</facial>
	<facial id="head_sleep_side" name="3/4 Front View - Sleep" enable="N">
        <selection type="ear" state_id="side_default"/>
        <selection type="eye" state_id="side_sleep"/>
        <selection type="eyebrow" state_id="side_default"/>
        <selection type="faceshape" state_id="side_default"/>
        <selection type="glasses" state_id="side_default"/>
        <selection type="hair" state_id="side_default"/>
        <selection type="mouth" state_id="side_sleep"/>
        <selection type="nose" state_id="side_default"/>
        <selection type="facedecoration" state_id="side_default"/>
	</facial>
	<facial id="head_lookdown_side" name="3/4 Front View - Look Down" enable="N">
        <selection type="ear" state_id="side_default"/>
        <selection type="eye" state_id="side_look_down"/>
        <selection type="eyebrow" state_id="side_default"/>
        <selection type="faceshape" state_id="side_default"/>
        <selection type="glasses" state_id="side_default"/>
        <selection type="hair" state_id="side_default"/>
        <selection type="mouth" state_id="side_default"/>
        <selection type="nose" state_id="side_default"/>
        <selection type="facedecoration" state_id="side_default"/>
	</facial>
	<facial id="head_scheme_side" name="3/4 Front View - Scheming" enable="N">
        <selection type="ear" state_id="side_default"/>
        <selection type="eye" state_id="side_scheme"/>
        <selection type="eyebrow" state_id="side_scheme"/>
        <selection type="faceshape" state_id="side_default"/>
        <selection type="glasses" state_id="side_default"/>
        <selection type="hair" state_id="side_default"/>
        <selection type="mouth" state_id="side_scheme"/>
        <selection type="nose" state_id="side_default"/>
        <selection type="facedecoration" state_id="side_default"/>
	</facial>

	<bodyshape id="default" name="Default" default_action="stand01" default_motion="walk" action_thumb="stand01" facial_thumb="head_neutral_front" thumb_path="thumbnail.swf" enable="Y">
		<default_char xscale="0.7" yscale="0.7" hxscale="1" hyscale="1" headdx="0" headdy="0">
			<tag>_sticky_filter_girl</tag>
			<color r="ccSkinColor">0xE2C294</color>
			<color r="ccEyeLib">0xBD8764</color>
			<color r="ccEyeIris">0x003333</color>
			<color r="ccMouthLip">0xB7796A</color>
			<color r="ccEyebrow">0x421D0B</color>
			<color r="ccBackMajor">0x996600</color>
			<component type="bodyshape" component_id="default" theme_id="infographics" x="0" y="0" xscale="1" yscale="1" offset="0" rotation="0" gobucks="0" gopoints="0"/>
			<component type="freeaction" component_id="default" theme_id="infographics" x="0" y="0" xscale="1" yscale="1" offset="0" rotation="0" gobucks="0" gopoints="0"/>
			<component type="faceshape" component_id="1001" theme_id="infographics" x="0" y="0" xscale="1" yscale="1" offset="0" rotation="0" split="N" gobucks="0" gopoints="0"/>
			<component type="mouth" component_id="1001" theme_id="infographics" x="0" y="0" xscale="1" yscale="1" offset="0" rotation="0" gobucks="0" gopoints="0"/>
			<component type="eye" component_id="1001" theme_id="infographics" x="0" y="0" xscale="1" yscale="1" offset="0" rotation="0" split="N" gobucks="0" gopoints="0"/>
			<component type="eyebrow" component_id="1001" theme_id="infographics" x="0" y="0" xscale="1" yscale="1" offset="0" rotation="0" split="N" gobucks="0" gopoints="0"/>
			<component type="nose" component_id="1001" theme_id="infographics" x="0" y="0" xscale="1" yscale="1" offset="0" rotation="0" gobucks="0" gopoints="0"/>
			<component type="hair" component_id="1001" theme_id="infographics" x="0" y="0" xscale="1" yscale="1" offset="0" rotation="0" gobucks="0" gopoints="0"/>
			<library type="GoHands" component_id="1001" theme_id="infographics" gobucks="0" gopoints="0"/>
			<library type="GoFeet" component_id="1001" theme_id="infographics" gobucks="0" gopoints="0"/>
			<library type="GoUpper" component_id="1001" theme_id="infographics" gobucks="0" gopoints="0"/>
			<library type="GoLower" component_id="1001" theme_id="infographics" gobucks="0" gopoints="0"/>
		</default_char>
		<default_char xscale="0.7" yscale="0.7" hxscale="1" hyscale="1" headdx="0" headdy="0">
			<tag>_sticky_filter_guy</tag>
			<color r="ccSkinColor">0xE2C294</color>
			<color r="ccEyeLib">0xBD8764</color>
			<color r="ccEyeIris">0x003333</color>
			<color r="ccMouthLip">0xB7796A</color>
			<color r="ccEyebrow">0x421D0B</color>
			<color r="ccBackMajor">0x996600</color>
			<component type="bodyshape" component_id="default" theme_id="infographics" x="0" y="0" xscale="1" yscale="1" offset="0" rotation="0" gobucks="0" gopoints="0"/>
			<component type="freeaction" component_id="default" theme_id="infographics" x="0" y="0" xscale="1" yscale="1" offset="0" rotation="0" gobucks="0" gopoints="0"/>
			<component type="faceshape" component_id="1001" theme_id="infographics" x="0" y="0" xscale="1" yscale="1" offset="0" rotation="0" split="N" gobucks="0" gopoints="0"/>
			<component type="eye" component_id="1001" theme_id="infographics" x="0" y="0" xscale="1" yscale="1" offset="0" rotation="0" split="N" gobucks="0" gopoints="0"/>
			<component type="nose" component_id="1001" theme_id="infographics" x="0" y="0" xscale="1" yscale="1" offset="0" rotation="0" gobucks="0" gopoints="0"/>
			<component type="mouth" component_id="1001" theme_id="infographics" x="0" y="0" xscale="1" yscale="1" offset="0" rotation="0" gobucks="0" gopoints="0"/>
			<component type="eyebrow" component_id="1001" theme_id="infographics" x="0" y="0" xscale="1" yscale="1" offset="0" rotation="0" split="N" gobucks="0" gopoints="0"/>
			<component type="hair" component_id="1001" theme_id="infographics" x="0" y="0" xscale="1" yscale="1" offset="0" rotation="0" gobucks="0" gopoints="0"/>
			<library type="GoHands" component_id="1001" theme_id="infographics" gobucks="0" gopoints="0"/>
			<library type="GoUpper" component_id="1001" theme_id="infographics" gobucks="0" gopoints="0"/>
			<library type="GoLower" component_id="1001" theme_id="infographics" gobucks="0" gopoints="0"/>
			<library type="GoFeet" component_id="1001" theme_id="infographics" gobucks="0" gopoints="0"/>
		</default_char>

		<actionpack id="standard" name="Standard" money="0" sharing="0" enable="Y">
            <action id="cc_leaning02" name="Leaning - one hand up" loop="Y" totalframe="60" enable="Y" is_motion="N">
                <selection type="facial" facial_id="head_neutral_front"/>
            </action>
            <action id="kneel" name="Kneel down" loop="Y" totalframe="60" enable="Y" is_motion="N">
                <selection type="facial" facial_id="head_neutral_side"/>
            </action>
            <action id="lying_down" name="Lying down" loop="Y" totalframe="60" enable="Y" is_motion="N">
                <selection type="facial" facial_id="head_sick_front"/>
            </action>
            <action id="mana_cool_06" name="Hand on hip" loop="Y" totalframe="60" enable="Y" is_motion="N">
                <selection type="facial" facial_id="head_neutral_front"/>
            </action>
            <action id="presenting_02" name="One arm - middle" loop="Y" totalframe="60" enable="Y" is_motion="N">
                <selection type="facial" facial_id="head_neutral_front"/>
            </action>
            <action id="presenting_03" name="One arm - down" loop="Y" totalframe="60" enable="Y" is_motion="N">
                <selection type="facial" facial_id="head_neutral_front"/>
            </action>
            <action id="presenting_04" name="Both arms - up" loop="Y" totalframe="60" enable="Y" is_motion="N">
                <selection type="facial" facial_id="head_neutral_front"/>
            </action>
            <action id="presenting_05" name="Both arms - up" loop="Y" totalframe="60" enable="Y" is_motion="N">
                <selection type="facial" facial_id="head_neutral_front"/>
            </action>
            <action id="presenting_06" name="Both arms - up" loop="Y" totalframe="60" enable="Y" is_motion="N">
                <selection type="facial" facial_id="head_neutral_front"/>
            </action>
            <action id="presenting_08" name="One arm - up" loop="Y" totalframe="60" enable="Y" is_motion="N">
                <selection type="facial" facial_id="head_neutral_front"/>
            </action>
            <action id="presenting_09" name="One arm - middle" loop="Y" totalframe="60" enable="Y" is_motion="N">
                <selection type="facial" facial_id="head_neutral_front"/>
            </action>
            <action id="presenting_10" name="One arm - middle" loop="Y" totalframe="60" enable="Y" is_motion="N">
                <selection type="facial" facial_id="head_neutral_front"/>
            </action>
            <action id="presenting_11" name="One arm - down" loop="Y" totalframe="60" enable="Y" is_motion="N">
                <selection type="facial" facial_id="head_neutral_front"/>
            </action>
            <action id="presenting_12" name="Kneeling" loop="Y" totalframe="60" enable="Y" is_motion="N">
                <selection type="facial" facial_id="head_neutral_side"/>
            </action>
            <action id="presenting_16" name="One arm - down" loop="Y" totalframe="60" enable="Y" is_motion="N">
                <selection type="facial" facial_id="head_neutral_front"/>
            </action>
            <action id="relax" name="Relax" loop="Y" totalframe="60" enable="Y" is_motion="N">
                <selection type="facial" facial_id="head_neutral_side"/>
            </action>
            <action id="run" name="Run" loop="Y" totalframe="60" enable="Y" is_motion="Y">
                <selection type="facial" facial_id="head_neutral_side"/>
            </action>
            <action id="sit_hand_front" name="Sitting" loop="Y" totalframe="60" enable="Y" is_motion="N">
                <selection type="facial" facial_id="head_neutral_side"/>
            </action>
            <action id="stand01" name="Standing" loop="Y" totalframe="60" enable="Y" is_motion="N">
                <selection type="facial" facial_id="head_neutral_front"/>
            </action>
            <action id="walk" name="Walk" loop="Y" totalframe="60" enable="Y" is_motion="Y">
                <selection type="facial" facial_id="head_neutral_side"/>
            </action>
		</actionpack>

		<library type="GoUpper" id="1001" path="1001" name="1001" thumb="1001_thumbnail.swf" display_order="10" money="0" sharing="0" enable="Y">
			<tag>_sticky_filter_guy</tag>
			<tag>_sticky_filter_girl</tag>
		</library>
		<library type="GoUpper" id="1002" path="1002" name="1002" thumb="1002_thumbnail.swf" display_order="10" money="0" sharing="0" enable="Y">
			<tag>_sticky_filter_guy</tag>
			<tag>_sticky_filter_girl</tag>
		</library>
		<library type="GoUpper" id="1003" path="1003" name="1003" thumb="1003_thumbnail.swf" display_order="10" money="0" sharing="0" enable="Y">
			<tag>_sticky_filter_guy</tag>
			<tag>_sticky_filter_girl</tag>
		</library>

		<library type="GoLower" id="1001" path="1001" name="1001" thumb="1001_thumbnail.swf" display_order="10" money="0" sharing="0" enable="Y">
			<tag>_sticky_filter_guy</tag>
			<tag>_sticky_filter_girl</tag>
		</library>
		<library type="GoLower" id="1002" path="1002" name="1002" thumb="1002_thumbnail.swf" display_order="10" money="0" sharing="0" enable="Y">
			<tag>_sticky_filter_guy</tag>
			<tag>_sticky_filter_girl</tag>
		</library>
		<library type="GoLower" id="1003" path="1003" name="1003" thumb="1003_thumbnail.swf" display_order="10" money="0" sharing="0" enable="Y">
			<tag>_sticky_filter_guy</tag>
			<tag>_sticky_filter_girl</tag>
		</library>

		<library type="GoHands" id="1001" path="1001" name="1001" thumb="1001_thumbnail.swf" display_order="10" money="0" sharing="0" enable="Y">
			<tag>_sticky_filter_guy</tag>
			<tag>_sticky_filter_girl</tag>
		</library>

		<library type="GoFeet" id="1001" path="1001" name="1001" thumb="1001_thumbnail.swf" display_order="10" money="0" sharing="0" enable="Y">
			<tag>_sticky_filter_guy</tag>
			<tag>_sticky_filter_girl</tag>
		</library>

		<component type="freeaction" id="default" path="default" name="default" thumb="" money="0" sharing="0" enable="Y"/>
	</bodyshape>

	<component type="eye" id="1001" path="1001" name="1001" thumb="thumbnail.swf" money="0" sharing="0" split="N" enable="Y">
		<state id="front_cry" filename="front_cry.swf"/>
		<state id="front_default" filename="front_default.swf"/>
		<state id="front_sick" filename="front_sick.swf"/>
		<state id="front_talk" filename="front_talk.swf"/>
		<state id="side_cry" filename="side_cry.swf"/>
		<state id="side_default" filename="side_default.swf"/>
		<state id="side_sick" filename="side_sick.swf"/>
		<state id="side_talk" filename="side_talk.swf"/>
		<state id="front_sleep" filename="front_sleep.swf"/>
		<state id="front_look_down" filename="front_look_down.swf"/>
		<state id="side_sleep" filename="side_sleep.swf"/>
		<state id="side_look_down" filename="side_look_down.swf"/>
		<state id="front_scheme" filename="front_scheme.swf"/>
		<state id="side_scheme" filename="side_scheme.swf"/>
		<tag>_sticky_filter_guy</tag>
		<tag>_sticky_filter_girl</tag>
	</component>

	<component type="eyebrow" id="1001" path="1001" name="1001" thumb="thumbnail.swf" money="0" sharing="0" split="N" enable="Y">
		<state id="front_angry" filename="front_angry.swf"/>
		<state id="front_confused" filename="front_confused.swf"/>
		<state id="front_default" filename="front_default.swf"/>
		<state id="front_sad" filename="front_sad.swf"/>
		<state id="front_sick" filename="front_sick.swf"/>
		<state id="front_talk" filename="front_talk.swf"/>
		<state id="side_angry" filename="side_angry.swf"/>
		<state id="side_confused" filename="side_confused.swf"/>
		<state id="side_default" filename="side_default.swf"/>
		<state id="side_sad" filename="side_sad.swf"/>
		<state id="side_sick" filename="side_sick.swf"/>
		<state id="side_talk" filename="side_talk.swf"/>
		<state id="front_scheme" filename="front_scheme.swf"/>
		<state id="side_scheme" filename="side_scheme.swf"/>
		<tag>_sticky_filter_guy</tag>
		<tag>_sticky_filter_girl</tag>
	</component>

	<component type="faceshape" id="1001" path="1001" name="1001" thumb="thumbnail.swf" money="0" sharing="0" split="N" enable="Y">
		<state id="front_default" filename="front_default.swf"/>
		<state id="side_default" filename="side_default.swf"/>
		<tag>_sticky_filter_guy</tag>
		<tag>_sticky_filter_girl</tag>
	</component>
	<component type="faceshape" id="1002" path="1002" name="1002" thumb="thumbnail.swf" money="0" sharing="0" split="N" enable="Y">
		<state id="front_default" filename="front_default.swf"/>
		<state id="side_default" filename="side_default.swf"/>
		<tag>_sticky_filter_guy</tag>
		<tag>_sticky_filter_girl</tag>
	</component>

	<component type="hair" id="1001" path="1001" name="1001" thumb="thumbnail.swf" money="0" sharing="0" enable="Y">
		<state id="front_default" filename="front_default.swf"/>
		<state id="side_default" filename="side_default.swf"/>
		<tag>_sticky_filter_guy</tag>
		<tag>_sticky_filter_girl</tag>
	</component>

	<component type="mouth" id="1001" path="1001" name="1001" thumb="thumbnail.swf" money="0" sharing="0" enable="Y">
		<state id="front_angry" filename="front_angry.swf"/>
		<state id="front_cry" filename="front_cry.swf"/>
		<state id="front_default" filename="front_default.swf"/>
		<state id="front_happy" filename="front_happy.swf"/>
		<state id="front_sad" filename="front_sad.swf"/>
		<state id="front_sick" filename="front_sick.swf"/>
		<state id="front_talk" filename="front_talk.swf"/>
		<state id="side_angry" filename="side_angry.swf"/>
		<state id="side_cry" filename="side_cry.swf"/>
		<state id="side_default" filename="side_default.swf"/>
		<state id="side_happy" filename="side_happy.swf"/>
		<state id="side_sad" filename="side_sad.swf"/>
		<state id="side_sick" filename="side_sick.swf"/>
		<state id="side_talk" filename="side_talk.swf"/>
		<state id="front_sleep" filename="front_sleep.swf"/>
		<state id="side_sleep" filename="side_sleep.swf"/>
		<state id="front_scheme" filename="front_scheme.swf"/>
		<state id="side_scheme" filename="side_scheme.swf"/>
		<tag>_sticky_filter_guy</tag>
		<tag>_sticky_filter_girl</tag>
	</component>

	<component type="nose" id="1001" path="1001" name="1001" thumb="thumbnail.swf" money="0" sharing="0" enable="Y">
		<state id="front_default" filename="front_default.swf"/>
		<state id="side_default" filename="side_default.swf"/>
		<tag>_sticky_filter_guy</tag>
		<tag>_sticky_filter_girl</tag>
	</component>

	<component type="glasses" id="1001" path="1001" name="1001" thumb="thumbnail.swf" money="0" sharing="0" enable="Y" split="N">
		<state id="front_default" filename="front_default.swf"/>
		<state id="side_default" filename="side_default.swf"/>
		<tag>_sticky_filter_guy</tag>
		<tag>_sticky_filter_girl</tag>
	</component>

</cc_theme>
